pichemist/__init__.py
pichemist/api.py
pichemist/charges.py
pichemist/cli.py
pichemist/config.py
pichemist/core.py
pichemist/io.py
pichemist/isoelectric.py
pichemist/model.py
pichemist/molecule.py
pichemist/plot.py
pichemist/stats.py
pichemist/utils.py
pichemist/data/fasta/convert_legacy_gauci_to_original_and_standardised.py
pichemist/data/fasta/convert_legacy_promost_into_standardised.py
pichemist/data/fasta/convert_legacy_short_set_to_original.py
pichemist/data/fasta/convert_original_short_set_to_standardised.py
pichemist/data/fasta/legacy_conversion.py
pichemist/data/fasta/legacy/aa_legend.tsv
pichemist/data/fasta/legacy/gauci.py
pichemist/data/fasta/legacy/promost.py
pichemist/data/fasta/legacy/short_pka_sets.py
pichemist/data/fasta/original_enriched/pka_set_gauci_original.json
pichemist/data/fasta/original_short/pka_set_bjellqvist_original.json
pichemist/data/fasta/original_short/pka_set_dawson_original.json
pichemist/data/fasta/original_short/pka_set_dtaselect_original.json
pichemist/data/fasta/original_short/pka_set_emboss_original.json
pichemist/data/fasta/original_short/pka_set_grimsley_original.json
pichemist/data/fasta/original_short/pka_set_ipc2_peptide_original.json
pichemist/data/fasta/original_short/pka_set_ipc_peptide_original.json
pichemist/data/fasta/original_short/pka_set_lehninger_original.json
pichemist/data/fasta/original_short/pka_set_nozaki_original.json
pichemist/data/fasta/original_short/pka_set_rodwell_original.json
pichemist/data/fasta/original_short/pka_set_sillero_original.json
pichemist/data/fasta/original_short/pka_set_solomon_original.json
pichemist/data/fasta/original_short/pka_set_thurlkill_original.json
pichemist/data/fasta/original_short/pka_set_toseland_original.json
pichemist/data/fasta/standardised/pka_set_bjellqvist_standardised.json
pichemist/data/fasta/standardised/pka_set_dawson_standardised.json
pichemist/data/fasta/standardised/pka_set_dtaselect_standardised.json
pichemist-2.1.1.dist-info/LICENSE
pichemist-2.1.1.dist-info/METADATA
pichemist-2.1.1.dist-info/WHEEL
pichemist-2.1.1.dist-info/entry_points.txt
pichemist-2.1.1.dist-info/top_level.txt
pichemist-2.1.1.dist-info/RECORD
