Metadata-Version: 2.1
Name: pichemist
Version: 2.1.1
Summary: Calculates the isoelectric point (pI) of a peptide/protein using the Henderson-Hasselbalch equation with the predicted pKa values of its amino acids.
Home-page: https://github.com/AstraZeneca/peptide-tools/tree/master/pIChemiSt
Author: Gian Marco Ghiandoni
Author-email: ghiandoni.g@gmail.com
License: Apache 2.0
License-File: LICENSE
Requires-Dist: matplotlib
Requires-Dist: rdkit
Requires-Dist: biopython
